README
setup.py
funniest/__init__.py
hello_pypi_world.egg-info/PKG-INFO
hello_pypi_world.egg-info/SOURCES.txt
hello_pypi_world.egg-info/dependency_links.txt
hello_pypi_world.egg-info/not-zip-safe
hello_pypi_world.egg-info/top_level.txt