Metadata-Version: 1.0
Name: hello-pypi-world
Version: 0.1
Summary: Simplest package ever
Home-page: http://github.com/mkarakus/hello_pypi_world
Author: mkarakus
Author-email: muratkarakus7@gmail.com
License: as it it is important :)
Platform: UNKNOWN
